setup.cfg
setup.py
easyastro/__init__.py
easyastro/test.py
easyastro.egg-info/PKG-INFO
easyastro.egg-info/SOURCES.txt
easyastro.egg-info/dependency_links.txt
easyastro.egg-info/requires.txt
easyastro.egg-info/top_level.txt
easyastro/aperture_photometry/__init__.py
easyastro/aperture_photometry/image_alignment.py
easyastro/light_curves/__init__.py
easyastro/light_curves/calculate_lightcurve.py
easyastro/light_curves/plan.py
easyastro/radial_velocity/__init__.py
easyastro/radial_velocity/fit_SB1.py
easyastro/radial_velocity/generate_radial_velocities.py