Metadata-Version: 1.1
Name: easyastro
Version: 0.2
Summary: Python source code dedicated to the Easy analysis of asttronomical data.
Home-page: https://github.com/samgill844/easyastro
Author: Samuel Gill
Author-email: s.gill@keele.ac.uk
License: GNU GPLv3
Platform: UNKNOWN
Classifier: Development Status :: 4 - Beta
